coinbase_pro/__init__.py
coinbase_pro/auth.py
coinbase_pro/client.py
myb_coinbase_pro_api-1.0.0.dist-info/LICENSE
myb_coinbase_pro_api-1.0.0.dist-info/METADATA
myb_coinbase_pro_api-1.0.0.dist-info/WHEEL
myb_coinbase_pro_api-1.0.0.dist-info/top_level.txt
myb_coinbase_pro_api-1.0.0.dist-info/RECORD
