Metadata-Version: 2.1
Name: myb-coinbase-pro-api
Version: 1.0.0
Summary: Python library for communicating with the Coinbase Pro API
Home-page: https://github.com/mine-your-business/myb-coinbase-pro-api
Author: Mine Your Business
Author-email: mine.your.business.crypto@gmail.com
License: GPL-3
Platform: UNKNOWN
Classifier: Programming Language :: Python :: 3
Classifier: License :: OSI Approved :: GNU General Public License v3 (GPLv3)
Classifier: Operating System :: OS Independent
Requires-Python: >=3.7
Requires-Dist: requests (>=2.22.0)
